repysitory/__init__.py
repysitory/connection_repository.py
repysitory/interface.py
repysitory/pool_repository.py
repysitory/vcr_repository.py
repysitory-0.1.0.dist-info/METADATA
repysitory-0.1.0.dist-info/WHEEL
repysitory-0.1.0.dist-info/RECORD
