Metadata-Version: 2.1
Name: repysitory
Version: 0.1.0
Summary: SOLID compatible python repositories.
Author: Nikita Vovchenko
Author-email: oldnote.public@gmail.com
Requires-Python: >=3.10,<4.0
Classifier: Programming Language :: Python :: 3
Classifier: Programming Language :: Python :: 3.10
Classifier: Programming Language :: Python :: 3.11
